mdformat_openmmlab/__init__.py
mdformat_openmmlab/gfm.py
mdformat_openmmlab/plugin.py
mdformat_openmmlab/table.py
mdformat_openmmlab/text.py
mdformat_openmmlab-0.0.4.dist-info/entry_points.txt
mdformat_openmmlab-0.0.4.dist-info/WHEEL
mdformat_openmmlab-0.0.4.dist-info/METADATA
mdformat_openmmlab-0.0.4.dist-info/RECORD
