Metadata-Version: 2.1
Name: mdformat_openmmlab
Version: 0.0.4
Summary: An mdformat plugin for...
Keywords: mdformat,markdown,markdown-it
Author-email: Ma Zerun <mzr1996@163.com>
Requires-Python: >=3.7
Classifier: Intended Audience :: Developers
Classifier: License :: OSI Approved :: MIT License
Classifier: Programming Language :: Python :: 3
Classifier: Topic :: Software Development :: Libraries :: Python Modules
Requires-Dist: mdformat >=0.7.0,<0.8.0
Requires-Dist: markdown-it-py[linkify]
Requires-Dist: mdit-py-plugins >=0.2.0,<0.4.0
Requires-Dist: pre-commit ; extra == "dev"
Requires-Dist: pytest~=6.0 ; extra == "test"
Requires-Dist: coverage ; extra == "test"
Requires-Dist: pytest-cov ; extra == "test"
Project-URL: Homepage, https://github.com/open-mmlab/mdformat-openmmlab
Provides-Extra: dev
Provides-Extra: test
